langgraph/checkpoint/postgres/__init__.py
langgraph/checkpoint/postgres/_ainternal.py
langgraph/checkpoint/postgres/_internal.py
langgraph/checkpoint/postgres/aio.py
langgraph/checkpoint/postgres/base.py
langgraph/checkpoint/postgres/py.typed
langgraph/checkpoint/postgres/shallow.py
langgraph/store/postgres/__init__.py
langgraph/store/postgres/aio.py
langgraph/store/postgres/base.py
langgraph/store/postgres/py.typed
langgraph_checkpoint_postgres-3.0.0.dist-info/METADATA
langgraph_checkpoint_postgres-3.0.0.dist-info/WHEEL
langgraph_checkpoint_postgres-3.0.0.dist-info/RECORD
