Metadata-Version: 2.4
Name: langgraph-checkpoint-postgres
Version: 3.0.0
Summary: Library with a Postgres implementation of LangGraph checkpoint saver.
Project-URL: Repository, https://www.github.com/langchain-ai/langgraph
License-Expression: MIT
Requires-Python: >=3.10
Requires-Dist: langgraph-checkpoint<4.0.0,>=2.1.2
Requires-Dist: orjson>=3.10.1
Requires-Dist: psycopg-pool>=3.2.0
Requires-Dist: psycopg>=3.2.0
